setup.py
recall/__init__.py
recall/client.py
recall/codec.py
recall/controller.py
recall/loadbalance.py
recall/server.py
recall/util.py
recall.egg-info/PKG-INFO
recall.egg-info/SOURCES.txt
recall.egg-info/dependency_links.txt
recall.egg-info/entry_points.txt
recall.egg-info/not-zip-safe
recall.egg-info/requires.txt
recall.egg-info/top_level.txt
recall/proto/__init__.py
recall/proto/rpc_meta_pb2.py
tests/test_proto/__init__.py
tests/test_proto/test_pb2.py