Metadata-Version: 1.1
Name: recall
Version: 0.2
Summary: Python High performance RPC framework based on protobuf
Home-page: https://github.com/airekans/recall
Author: Yaolong Huang
Author-email: airekans@gmail.com
License: MIT
Keywords: rpc gevent
Platform: UNKNOWN
Classifier: Development Status :: 3 - Alpha
Classifier: Environment :: Web Environment
Classifier: Intended Audience :: Developers
Classifier: License :: OSI Approved :: MIT License
Classifier: Operating System :: POSIX
Classifier: Programming Language :: Python
Classifier: Programming Language :: Python :: 2.7
Classifier: Topic :: Internet
